{
  "project_info": {
    "project_number": "1012021599388",
    "project_id": "myft-a9fc5",
    "storage_bucket": "myft-a9fc5.firebasestorage.app"
  },
  "client": [
    {
      "client_info": {
        "mobilesdk_app_id": "1:1012021599388:android:e16a24b90d74dcf3702159",
        "android_client_info": {
          "package_name": "com.zennxt.myfoodtracker"
        }
      },
      "oauth_client": [],
      "api_key": [
        {
          "current_key": "AIzaSyB4HyiAlbFXVHJ3v9kEAz5PBi-_Tpa309s"
        }
      ],
      "services": {
        "appinvite_service": {
          "other_platform_oauth_client": []
        }
      }
    }
  ],
  "configuration_version": "1"
}